ncon/__init__.py
ncon/ncon.py
ncon-2.0.0.dist-info/LICENSE
ncon-2.0.0.dist-info/METADATA
ncon-2.0.0.dist-info/WHEEL
ncon-2.0.0.dist-info/top_level.txt
ncon-2.0.0.dist-info/RECORD
