Metadata-Version: 2.1
Name: ncon
Version: 2.0.0
Summary: Tensor network contraction function for Python 3.
Home-page: https://github.com/mhauru/ncon
Author: Markus Hauru
Author-email: markus@mhauru.org
License: MIT
Keywords: tensor networks
Classifier: Programming Language :: Python :: 3
Classifier: License :: OSI Approved :: MIT License
Classifier: Operating System :: OS Independent
Classifier: Topic :: Scientific/Engineering
Requires-Python: >=3.6
License-File: LICENSE
Requires-Dist: numpy (>=1.11.0)
Provides-Extra: tests
Requires-Dist: pytest ; extra == 'tests'
Requires-Dist: coverage ; extra == 'tests'
Requires-Dist: pytest-cov ; extra == 'tests'
